nonebot_plugin_reboot/__init__.py
nonebot_plugin_reboot/command.py
nonebot_plugin_reboot/config.py
nonebot_plugin_reboot/reloader.py
nonebot_plugin_reboot-0.1.4.dist-info/LICENSE
nonebot_plugin_reboot-0.1.4.dist-info/METADATA
nonebot_plugin_reboot-0.1.4.dist-info/WHEEL
nonebot_plugin_reboot-0.1.4.dist-info/RECORD
