Metadata-Version: 2.1
Name: nonebot-plugin-reboot
Version: 0.1.4
Summary: Reboot your bot by using command
Home-page: https://github.com/18870/nonebot-plugin-reboot
License: MIT
Keywords: nonebot
Author: 18870
Author-email: a20110123@163.com
Requires-Python: >=3.7.3,<4.0.0
Classifier: License :: OSI Approved :: MIT License
Classifier: Programming Language :: Python :: 3
Classifier: Programming Language :: Python :: 3.8
Classifier: Programming Language :: Python :: 3.9
Classifier: Programming Language :: Python :: 3.10
Classifier: Programming Language :: Python :: 3.11
Requires-Dist: nonebot-adapter-onebot (>=2.1.0,<3.0.0)
Requires-Dist: nonebot2 (>=2.0.0-beta.2,<3.0.0)
Project-URL: Repository, https://github.com/18870/nonebot-plugin-reboot
